Joson_yaml_pytest/__init__.py
Joson_yaml_pytest/create_funtion.py
Joson_yaml_pytest/db.py
Joson_yaml_pytest/exceptions.py
Joson_yaml_pytest/extract.py
Joson_yaml_pytest/http_session.py
Joson_yaml_pytest/log.py
Joson_yaml_pytest/my_builtins.py
Joson_yaml_pytest/parser.py
Joson_yaml_pytest/plugin.py
Joson_yaml_pytest/render_template_obj.py
Joson_yaml_pytest/report_notify.py
Joson_yaml_pytest/request_session.py
Joson_yaml_pytest/runner.py
Joson_yaml_pytest/swagger_parser.py
Joson_yaml_pytest/validate.py
Joson_yaml_pytest-1.2.7.dist-info/METADATA
Joson_yaml_pytest-1.2.7.dist-info/WHEEL
Joson_yaml_pytest-1.2.7.dist-info/entry_points.txt
Joson_yaml_pytest-1.2.7.dist-info/top_level.txt
Joson_yaml_pytest-1.2.7.dist-info/RECORD
