Metadata-Version: 2.1
Name: Joson-yaml-pytest
Version: 1.2.7
Summary: http/https API run by yaml
Home-page: https://github.com/Joson/Joson_yaml_pytest
Author: Bkex-QA-Joson
Author-email: 994991952@qq.com
License: proprietary
Keywords: pytest,py.test,pytest-yaml,Joson_yaml_pytest
Platform: UNKNOWN
Classifier: Framework :: Pytest
Classifier: Programming Language :: Python
Classifier: Topic :: Software Development :: Testing
Classifier: Programming Language :: Python :: 3.9
Requires-Python: >=3.9
Requires-Dist: Jinja2 (>=3.1.2)
Requires-Dist: jmespath (>=0.9.5)
Requires-Dist: jsonpath (>=0.82)
Requires-Dist: pytest (>=7.2.0)
Requires-Dist: PyYAML (>=6.0)
Requires-Dist: requests (==2.18.4)
Requires-Dist: allure-pytest (>=2.12.0)
Requires-Dist: pymysql (>=1.0.2)
Requires-Dist: DingtalkChatbot (>=1.5.7)
Requires-Dist: Faker (>=15.3.4)
Requires-Dist: requests-toolbelt (>=0.10.1)
